Lab 1/2018A7PS0097G_Lab1.v
//ShifterAndALU.v

// select 0 = in0 1 = in1
module mux2to1_3bit(input [2:0] in0, input [2:0] in1, input select, output reg [2:0] muxOut);   // mux whose o/p is fed to barrel shifter
  //WRITE CODE HERE
  
    always @(in0,in1,select)        // executes when any 1 (or more) of these 3 change
        begin
            case(select)
                  1'b0: muxOut = in0;
                  1'b1: muxOut = in1;
            endcase
        end
endmodule



// select 0 = in0 1 = in1
module mux2to1_8bit(input [7:0] in0, input [7:0] in1, input select, output reg [7:0] muxOut);   // Last mux that (gives the output)
   //WRITE CODE HERE
    always @(in0,in1,select)      
        begin
            case(select)
                1'b0: muxOut = in0;         // ALU one
                1'b1: muxOut = in1;         // Barrel Shifter one
            endcase
        end
endmodule


module mux8to1_1bit(input in0, input in1, input in2, input in3, input in4, input in5, input in6, input in7, input[2:0] select,output reg muxOut);
   //WRITE CODE HERE

   // This mux is used in designing the barrel shifter

    always@(in0,in1,in2,in3,in4,in5,in6,in7,select)
        begin
            case(select)
                3'b000: muxOut = in0;
                3'b001: muxOut = in1;
                3'b010: muxOut = in2;
                3'b011: muxOut = in3;
                3'b100: muxOut = in4;
                3'b101: muxOut = in5;
                3'b110: muxOut = in6;
                3'b111: muxOut = in7;
            endcase
        end
endmodule

module barrelshifter(input[2:0] shiftAmt, input[7:0] b, input[2:0] oper, output[7:0] shiftOut);
	   //WRITE CODE HERE
     
       wire [2:0] Aout;
       wire [2:0] Bout;
       wire [2:0] Cout;

       // Aout, Bout, Cout act as select in mux
       wire [7:0] s;
       wire [7:0] r;

       mux2to1_3bit mux2to1_3_call_1(3'b000, oper, shiftAmt[0], Aout);
       mux2to1_3bit mux2to1_3_call_2(3'b000, oper, shiftAmt[1], Bout);
       mux2to1_3bit mux2to1_3_call_3(3'b000, oper, shiftAmt[2], Cout);

       mux8to1_1bit mux8to1_1_call_1(b[0], b[1], b[1], b[1], 1'b0, b[7], 1'b0, 1'b0, Aout, s[0]);
       mux8to1_1bit mux8to1_1_call_2(b[1], b[2], b[2], b[2], b[0], b[0], 1'b0, 1'b0, Aout, s[1]);
       mux8to1_1bit mux8to1_1_call_3(b[2], b[3], b[3], b[3], b[1], b[1], 1'b0, 1'b0, Aout, s[2]);
       mux8to1_1bit mux8to1_1_call_4(b[3], b[4], b[4], b[4], b[2], b[2], 1'b0, 1'b0, Aout, s[3]);
       mux8to1_1bit mux8to1_1_call_5(b[4], b[5], b[5], b[5], b[3], b[3], 1'b0, 1'b0, Aout, s[4]);
       mux8to1_1bit mux8to1_1_call_6(b[5], b[6], b[6], b[6], b[4], b[4], 1'b0, 1'b0, Aout, s[5]);
       mux8to1_1bit mux8to1_1_call_7(b[6], b[7], b[7], b[7], b[5], b[5], 1'b0, 1'b0, Aout, s[6]);
       mux8to1_1bit mux8to1_1_call_8(b[7], b[7], 1'b0, b[0], b[6], b[6], 1'b0, 1'b0, Aout, s[7]);

       mux8to1_1bit mux8to1_1_call1_1(s[0], s[2], s[2], s[2], 1'b0, s[6], 1'b0, 1'b0, Bout, r[0]);
       mux8to1_1bit mux8to1_1_call1_2(s[1], s[3], s[3], s[3], 1'b0, s[7], 1'b0, 1'b0, Bout, r[1]);
       mux8to1_1bit mux8to1_1_call1_3(s[2], s[4], s[4], s[4], s[0], s[0], 1'b0, 1'b0, Bout, r[2]);
       mux8to1_1bit mux8to1_1_call1_4(s[3], s[5], s[5], s[5], s[1], s[1], 1'b0, 1'b0, Bout, r[3]);
       mux8to1_1bit mux8to1_1_call1_5(s[4], s[6], s[6], s[6], s[2], s[2], 1'b0, 1'b0, Bout, r[4]);
       mux8to1_1bit mux8to1_1_call1_6(s[5], s[7], s[7], s[7], s[3], s[3], 1'b0, 1'b0, Bout, r[5]);
       mux8to1_1bit mux8to1_1_call1_7(s[6], s[7], 1'b0, s[0], s[4], s[4], 1'b0, 1'b0, Bout, r[6]);
       mux8to1_1bit mux8to1_1_call1_8(s[7], s[7], 1'b0, s[1], s[5], s[5], 1'b0, 1'b0, Bout, r[7]);

       mux8to1_1bit mux8to1_1_call2_1(r[0], r[4], r[4], r[4], 1'b0, r[4], 1'b0, 1'b0, Cout, shiftOut[0]);
       mux8to1_1bit mux8to1_1_call2_2(r[1], r[5], r[5], r[5], 1'b0, r[5], 1'b0, 1'b0, Cout, shiftOut[1]);
       mux8to1_1bit mux8to1_1_call2_3(r[2], r[6], r[6], r[6], 1'b0, r[6], 1'b0, 1'b0, Cout, shiftOut[2]);
       mux8to1_1bit mux8to1_1_call2_4(r[3], r[7], r[7], r[7], 1'b0, r[7], 1'b0, 1'b0, Cout, shiftOut[3]);
       mux8to1_1bit mux8to1_1_call2_5(r[4], r[7], 1'b0, r[0], r[0], r[0], 1'b0, 1'b0, Cout, shiftOut[4]);
       mux8to1_1bit mux8to1_1_call2_6(r[5], r[7], 1'b0, r[1], r[1], r[1], 1'b0, 1'b0, Cout, shiftOut[5]);
       mux8to1_1bit mux8to1_1_call2_7(r[6], r[7], 1'b0, r[2], r[2], r[2], 1'b0, 1'b0, Cout, shiftOut[6]);
       mux8to1_1bit mux8to1_1_call2_8(r[7], r[7], 1'b0, r[3], r[3], r[3], 1'b0, 1'b0, Cout, shiftOut[7]);

endmodule

// Alu operations are: 00 for alu1, 01 for add, 10 for sub(alu1-alu2) , 11 for AND, 100 for OR and 101 for NOT(alu1)
module alu(input [7:0] aluIn1, input [7:0] aluIn2, input [2:0]aluOp, output reg [7:0] aluOut);
       //WRITE CODE HERE

    always@(aluIn1,aluIn2,aluOp)
        begin
            case(aluOp)
                3'b000:aluOut = aluIn1;
                3'b001:aluOut = aluIn1 + aluIn2;
                3'b010:aluOut = aluIn1 - aluIn2;
                3'b011:aluOut = aluIn1 & aluIn2;
                3'b100:aluOut = aluIn1 | aluIn2;
                3'b101:aluOut = ~ aluIn1;
                default: aluOut=0;
            endcase
        end       

endmodule


module shifterAndALU(input [7:0]inp1, input [7:0] inp2, input [2:0]shiftlmm, input selShiftAmt, input [2:0]oper, input selOut, output [7:0] out);
	   //WRITE CODE HERE

       wire [7:0] shiftOut;
       wire [2:0] shiftAmt;
       wire [7:0] aluOut;

       // barrelshifter part
       mux2to1_3bit mux2to1_3_call(inp2[2:0], shiftlmm, selShiftAmt, shiftAmt); 
       barrelshifter bshifter_call(shiftAmt, inp1, oper, shiftOut);

       // ALU part 
       alu alu_call(inp1, inp2, oper, aluOut);

      // gives the final output
       mux2to1_8bit mux2to1_8_call(aluOut, shiftOut, selOut, out);                    


endmodule

//TestBench ALU
module testbenchALU();
	// Input
	reg [7:0] inp1, inp2;
	reg [2:0] aluOp;
	reg [2:0] shiftlmm;
	reg selShiftAmt, selOut;
	// Output
	wire [7:0] aluOut;

	shifterAndALU shifterAndALU_Test (inp1, inp2, shiftlmm, selShiftAmt, aluOp, selOut, aluOut);

	initial
		begin
			$dumpfile("testALU.vcd");
     	$dumpvars(0,testbenchALU);
			inp1 = 8'd80; //80 in binary is 1010000
			inp2 = 8'd20; //20 in binary is 10100   
			shiftlmm = 3'b010; 
			
			aluOp=3'd0; selOut = 1'b0;// normal output = 80

			#10 aluOp = 3'd0; selOut = 1'b1; selShiftAmt = 1'b1; //No shift output = 80

			#10 aluOp=3'd1; selOut = 1'b0;// normal add	output => 20 + 80 = 100

			#10 aluOp = 3'd1; selOut = 1'b1; selShiftAmt = 1'b1; // arithmetic shift right of 80 by 2 places = 20

			#10 aluOp=3'd2; selOut = 1'b0; // normal sub output => 80 - 20 = 60

			#10 aluOp = 3'd2; selOut = 1'b1; selShiftAmt = 1'b0; // logical shift right of 80 by 4 places = 0

			#10 aluOp=3'd3; selOut = 1'b0;// normal and output => 80 & 20 = 16

			#10 aluOp = 3'd3; selOut = 1'b1; selShiftAmt = 1'b0; // Circular Shift Right of 80 by 4 places = 5

			#10 aluOp=3'd4; selOut = 1'b0;// normal or output => 80 | 20 = 84

			#10 aluOp = 3'd4; selOut = 1'b1; selShiftAmt = 1'b1; // Logical Shift Left of 80 by 2 bits = 64

			#10 aluOp=3'd5; selOut = 1'b0; // normal not of 80 = 175

			#10 aluOp = 3'd5; selOut = 1'b1; selShiftAmt = 1'b0; // Circular left shift of 80 by 4 bits = 5

			#10 inp1=8'd15; inp2=8'd26; aluOp=3'd2; selOut = 1'b0;//sub overflow 
			// (15 - 26) = -11 and its a 8 bit number so, 256-11 = 245 output => 245 (since it is unsigned decimal)

			#10 inp1=8'd150; inp2=8'd150; aluOp=3'd1; selOut = 1'b0;// add overflow
			//(150+150) = 300 and its a 8 bit number so, 300-256 = 44 output=> 44.

			#10 inp1=8'b0000_0000; aluOp=3'd5; selOut = 1'b0;//not overflow
			// not(0) = all 1. Since its a 8 bit number output=>255

			#10 $finish;
		end

endmodule

Lab 1/2018A7PS0097G_Lab1.vcd
$date
	Tue Sep 01 13:36:34 2020
$end
$version
	Icarus Verilog
$end
$timescale
	1s
$end
$scope module testbenchALU $end
$var wire 8 ! aluOut [7:0] $end
$var reg 3 " aluOp [2:0] $end
$var reg 8 # inp1 [7:0] $end
$var reg 8 $ inp2 [7:0] $end
$var reg 1 % selOut $end
$var reg 1 & selShiftAmt $end
$var reg 3 ' shiftlmm [2:0] $end
$scope module shifterAndALU_Test $end
$var wire 8 ( inp1 [7:0] $end
$var wire 8 ) inp2 [7:0] $end
$var wire 3 * oper [2:0] $end
$var wire 1 % selOut $end
$var wire 1 & selShiftAmt $end
$var wire 3 + shiftlmm [2:0] $end
$var wire 8 , shiftOut [7:0] $end
$var wire 3 - shiftAmt [2:0] $end
$var wire 8 . out [7:0] $end
$var wire 8 / aluOut [7:0] $end
$scope module alu_call $end
$var wire 8 0 aluIn1 [7:0] $end
$var wire 8 1 aluIn2 [7:0] $end
$var wire 3 2 aluOp [2:0] $end
$var reg 8 3 aluOut [7:0] $end
$upscope $end
$scope module bshifter_call $end
$var wire 8 4 b [7:0] $end
$var wire 3 5 oper [2:0] $end
$var wire 8 6 shiftOut [7:0] $end
$var wire 3 7 shiftAmt [2:0] $end
$var wire 8 8 s [7:0] $end
$var wire 8 9 r [7:0] $end
$var wire 3 : Cout [2:0] $end
$var wire 3 ; Bout [2:0] $end
$var wire 3 < Aout [2:0] $end
$scope module mux2to1_3_call_1 $end
$var wire 3 = in0 [2:0] $end
$var wire 3 > in1 [2:0] $end
$var wire 1 ? select $end
$var reg 3 @ muxOut [2:0] $end
$upscope $end
$scope module mux2to1_3_call_2 $end
$var wire 3 A in0 [2:0] $end
$var wire 3 B in1 [2:0] $end
$var wire 1 C select $end
$var reg 3 D muxOut [2:0] $end
$upscope $end
$scope module mux2to1_3_call_3 $end
$var wire 3 E in0 [2:0] $end
$var wire 3 F in1 [2:0] $end
$var wire 1 G select $end
$var reg 3 H muxOut [2:0] $end
$upscope $end
$scope module mux8to1_1_call1_1 $end
$var wire 1 I in0 $end
$var wire 1 J in1 $end
$var wire 1 K in2 $end
$var wire 1 L in3 $end
$var wire 1 M in4 $end
$var wire 1 N in5 $end
$var wire 1 O in6 $end
$var wire 1 P in7 $end
$var wire 3 Q select [2:0] $end
$var reg 1 R muxOut $end
$upscope $end
$scope module mux8to1_1_call1_2 $end
$var wire 1 S in0 $end
$var wire 1 T in1 $end
$var wire 1 U in2 $end
$var wire 1 V in3 $end
$var wire 1 W in4 $end
$var wire 1 X in5 $end
$var wire 1 Y in6 $end
$var wire 1 Z in7 $end
$var wire 3 [ select [2:0] $end
$var reg 1 \ muxOut $end
$upscope $end
$scope module mux8to1_1_call1_3 $end
$var wire 1 ] in0 $end
$var wire 1 ^ in1 $end
$var wire 1 _ in2 $end
$var wire 1 ` in3 $end
$var wire 1 a in4 $end
$var wire 1 b in5 $end
$var wire 1 c in6 $end
$var wire 1 d in7 $end
$var wire 3 e select [2:0] $end
$var reg 1 f muxOut $end
$upscope $end
$scope module mux8to1_1_call1_4 $end
$var wire 1 g in0 $end
$var wire 1 h in1 $end
$var wire 1 i in2 $end
$var wire 1 j in3 $end
$var wire 1 k in4 $end
$var wire 1 l in5 $end
$var wire 1 m in6 $end
$var wire 1 n in7 $end
$var wire 3 o select [2:0] $end
$var reg 1 p muxOut $end
$upscope $end
$scope module mux8to1_1_call1_5 $end
$var wire 1 q in0 $end
$var wire 1 r in1 $end
$var wire 1 s in2 $end
$var wire 1 t in3 $end
$var wire 1 u in4 $end
$var wire 1 v in5 $end
$var wire 1 w in6 $end
$var wire 1 x in7 $end
$var wire 3 y select [2:0] $end
$var reg 1 z muxOut $end
$upscope $end
$scope module mux8to1_1_call1_6 $end
$var wire 1 { in0 $end
$var wire 1 | in1 $end
$var wire 1 } in2 $end
$var wire 1 ~ in3 $end
$var wire 1 !" in4 $end
$var wire 1 "" in5 $end
$var wire 1 #" in6 $end
$var wire 1 $" in7 $end
$var wire 3 %" select [2:0] $end
$var reg 1 &" muxOut $end
$upscope $end
$scope module mux8to1_1_call1_7 $end
$var wire 1 '" in0 $end
$var wire 1 (" in1 $end
$var wire 1 )" in2 $end
$var wire 1 *" in3 $end
$var wire 1 +" in4 $end
$var wire 1 ," in5 $end
$var wire 1 -" in6 $end
$var wire 1 ." in7 $end
$var wire 3 /" select [2:0] $end
$var reg 1 0" muxOut $end
$upscope $end
$scope module mux8to1_1_call1_8 $end
$var wire 1 1" in0 $end
$var wire 1 2" in1 $end
$var wire 1 3" in2 $end
$var wire 1 4" in3 $end
$var wire 1 5" in4 $end
$var wire 1 6" in5 $end
$var wire 1 7" in6 $end
$var wire 1 8" in7 $end
$var wire 3 9" select [2:0] $end
$var reg 1 :" muxOut $end
$upscope $end
$scope module mux8to1_1_call2_1 $end
$var wire 1 ;" in0 $end
$var wire 1 <" in1 $end
$var wire 1 =" in2 $end
$var wire 1 >" in3 $end
$var wire 1 ?" in4 $end
$var wire 1 @" in5 $end
$var wire 1 A" in6 $end
$var wire 1 B" in7 $end
$var wire 3 C" select [2:0] $end
$var reg 1 D" muxOut $end
$upscope $end
$scope module mux8to1_1_call2_2 $end
$var wire 1 E" in0 $end
$var wire 1 F" in1 $end
$var wire 1 G" in2 $end
$var wire 1 H" in3 $end
$var wire 1 I" in4 $end
$var wire 1 J" in5 $end
$var wire 1 K" in6 $end
$var wire 1 L" in7 $end
$var wire 3 M" select [2:0] $end
$var reg 1 N" muxOut $end
$upscope $end
$scope module mux8to1_1_call2_3 $end
$var wire 1 O" in0 $end
$var wire 1 P" in1 $end
$var wire 1 Q" in2 $end
$var wire 1 R" in3 $end
$var wire 1 S" in4 $end
$var wire 1 T" in5 $end
$var wire 1 U" in6 $end
$var wire 1 V" in7 $end
$var wire 3 W" select [2:0] $end
$var reg 1 X" muxOut $end
$upscope $end
$scope module mux8to1_1_call2_4 $end
$var wire 1 Y" in0 $end
$var wire 1 Z" in1 $end
$var wire 1 [" in2 $end
$var wire 1 \" in3 $end
$var wire 1 ]" in4 $end
$var wire 1 ^" in5 $end
$var wire 1 _" in6 $end
$var wire 1 `" in7 $end
$var wire 3 a" select [2:0] $end
$var reg 1 b" muxOut $end
$upscope $end
$scope module mux8to1_1_call2_5 $end
$var wire 1 c" in0 $end
$var wire 1 d" in1 $end
$var wire 1 e" in2 $end
$var wire 1 f" in3 $end
$var wire 1 g" in4 $end
$var wire 1 h" in5 $end
$var wire 1 i" in6 $end
$var wire 1 j" in7 $end
$var wire 3 k" select [2:0] $end
$var reg 1 l" muxOut $end
$upscope $end
$scope module mux8to1_1_call2_6 $end
$var wire 1 m" in0 $end
$var wire 1 n" in1 $end
$var wire 1 o" in2 $end
$var wire 1 p" in3 $end
$var wire 1 q" in4 $end
$var wire 1 r" in5 $end
$var wire 1 s" in6 $end
$var wire 1 t" in7 $end
$var wire 3 u" select [2:0] $end
$var reg 1 v" muxOut $end
$upscope $end
$scope module mux8to1_1_call2_7 $end
$var wire 1 w" in0 $end
$var wire 1 x" in1 $end
$var wire 1 y" in2 $end
$var wire 1 z" in3 $end
$var wire 1 {" in4 $end
$var wire 1 |" in5 $end
$var wire 1 }" in6 $end
$var wire 1 ~" in7 $end
$var wire 3 !# select [2:0] $end
$var reg 1 "# muxOut $end
$upscope $end
$scope module mux8to1_1_call2_8 $end
$var wire 1 ## in0 $end
$var wire 1 $# in1 $end
$var wire 1 %# in2 $end
$var wire 1 &# in3 $end
$var wire 1 '# in4 $end
$var wire 1 (# in5 $end
$var wire 1 )# in6 $end
$var wire 1 *# in7 $end
$var wire 3 +# select [2:0] $end
$var reg 1 ,# muxOut $end
$upscope $end
$scope module mux8to1_1_call_1 $end
$var wire 1 -# in0 $end
$var wire 1 .# in1 $end
$var wire 1 /# in2 $end
$var wire 1 0# in3 $end
$var wire 1 1# in4 $end
$var wire 1 2# in5 $end
$var wire 1 3# in6 $end
$var wire 1 4# in7 $end
$var wire 3 5# select [2:0] $end
$var reg 1 6# muxOut $end
$upscope $end
$scope module mux8to1_1_call_2 $end
$var wire 1 7# in0 $end
$var wire 1 8# in1 $end
$var wire 1 9# in2 $end
$var wire 1 :# in3 $end
$var wire 1 ;# in4 $end
$var wire 1 <# in5 $end
$var wire 1 =# in6 $end
$var wire 1 ># in7 $end
$var wire 3 ?# select [2:0] $end
$var reg 1 @# muxOut $end
$upscope $end
$scope module mux8to1_1_call_3 $end
$var wire 1 A# in0 $end
$var wire 1 B# in1 $end
$var wire 1 C# in2 $end
$var wire 1 D# in3 $end
$var wire 1 E# in4 $end
$var wire 1 F# in5 $end
$var wire 1 G# in6 $end
$var wire 1 H# in7 $end
$var wire 3 I# select [2:0] $end
$var reg 1 J# muxOut $end
$upscope $end
$scope module mux8to1_1_call_4 $end
$var wire 1 K# in0 $end
$var wire 1 L# in1 $end
$var wire 1 M# in2 $end
$var wire 1 N# in3 $end
$var wire 1 O# in4 $end
$var wire 1 P# in5 $end
$var wire 1 Q# in6 $end
$var wire 1 R# in7 $end
$var wire 3 S# select [2:0] $end
$var reg 1 T# muxOut $end
$upscope $end
$scope module mux8to1_1_call_5 $end
$var wire 1 U# in0 $end
$var wire 1 V# in1 $end
$var wire 1 W# in2 $end
$var wire 1 X# in3 $end
$var wire 1 Y# in4 $end
$var wire 1 Z# in5 $end
$var wire 1 [# in6 $end
$var wire 1 \# in7 $end
$var wire 3 ]# select [2:0] $end
$var reg 1 ^# muxOut $end
$upscope $end
$scope module mux8to1_1_call_6 $end
$var wire 1 _# in0 $end
$var wire 1 `# in1 $end
$var wire 1 a# in2 $end
$var wire 1 b# in3 $end
$var wire 1 c# in4 $end
$var wire 1 d# in5 $end
$var wire 1 e# in6 $end
$var wire 1 f# in7 $end
$var wire 3 g# select [2:0] $end
$var reg 1 h# muxOut $end
$upscope $end
$scope module mux8to1_1_call_7 $end
$var wire 1 i# in0 $end
$var wire 1 j# in1 $end
$var wire 1 k# in2 $end
$var wire 1 l# in3 $end
$var wire 1 m# in4 $end
$var wire 1 n# in5 $end
$var wire 1 o# in6 $end
$var wire 1 p# in7 $end
$var wire 3 q# select [2:0] $end
$var reg 1 r# muxOut $end
$upscope $end
$scope module mux8to1_1_call_8 $end
$var wire 1 s# in0 $end
$var wire 1 t# in1 $end
$var wire 1 u# in2 $end
$var wire 1 v# in3 $end
$var wire 1 w# in4 $end
$var wire 1 x# in5 $end
$var wire 1 y# in6 $end
$var wire 1 z# in7 $end
$var wire 3 {# select [2:0] $end
$var reg 1 |# muxOut $end
$upscope $end
$upscope $end
$scope module mux2to1_3_call $end
$var wire 3 }# in0 [2:0] $end
$var wire 3 ~# in1 [2:0] $end
$var wire 1 & select $end
$var reg 3 !$ muxOut [2:0] $end
$upscope $end
$scope module mux2to1_8_call $end
$var wire 8 "$ in0 [7:0] $end
$var wire 8 #$ in1 [7:0] $end
$var wire 1 % select $end
$var reg 8 $$ muxOut [7:0] $end
$upscope $end
$upscope $end
$upscope $end
$enddefinitions $end
#0
$dumpvars
b1010000 $$
bx #$
b1010000 "$
bx !$
b10 ~#
b100 }#
x|#
bx {#
0z#
0y#
1x#
1w#
0v#
0u#
0t#
0s#
xr#
bx q#
0p#
0o#
0n#
0m#
0l#
0k#
0j#
1i#
xh#
bx g#
0f#
0e#
1d#
1c#
1b#
1a#
1`#
0_#
x^#
bx ]#
0\#
0[#
0Z#
0Y#
0X#
0W#
0V#
1U#
xT#
bx S#
0R#
0Q#
0P#
0O#
1N#
1M#
1L#
0K#
xJ#
bx I#
0H#
0G#
0F#
0E#
0D#
0C#
0B#
0A#
x@#
bx ?#
0>#
0=#
0<#
0;#
0:#
09#
08#
07#
x6#
bx 5#
04#
03#
02#
01#
00#
0/#
0.#
0-#
x,#
bx +#
0*#
0)#
x(#
x'#
x&#
0%#
x$#
x##
x"#
bx !#
0~"
0}"
x|"
x{"
xz"
0y"
xx"
xw"
xv"
bx u"
0t"
0s"
xr"
xq"
xp"
0o"
xn"
xm"
xl"
bx k"
0j"
0i"
xh"
xg"
xf"
0e"
xd"
xc"
xb"
bx a"
0`"
0_"
x^"
0]"
x\"
x["
xZ"
xY"
xX"
bx W"
0V"
0U"
xT"
0S"
xR"
xQ"
xP"
xO"
xN"
bx M"
0L"
0K"
xJ"
0I"
xH"
xG"
xF"
xE"
xD"
bx C"
0B"
0A"
x@"
0?"
x>"
x="
x<"
x;"
x:"
bx 9"
08"
07"
x6"
x5"
x4"
03"
x2"
x1"
x0"
bx /"
0."
0-"
x,"
x+"
x*"
0)"
x("
x'"
x&"
bx %"
0$"
0#"
x""
x!"
x~
x}
x|
x{
xz
bx y
0x
0w
xv
xu
xt
xs
xr
xq
xp
bx o
0n
0m
xl
xk
xj
xi
xh
xg
xf
bx e
0d
0c
xb
xa
x`
x_
x^
x]
x\
bx [
0Z
0Y
xX
0W
xV
xU
xT
xS
xR
bx Q
0P
0O
xN
0M
xL
xK
xJ
xI
bx H
xG
b0 F
b0 E
bx D
xC
b0 B
b0 A
bx @
x?
b0 >
b0 =
bx <
bx ;
bx :
bx 9
bx 8
bx 7
bx 6
b0 5
b1010000 4
b1010000 3
b0 2
b10100 1
b1010000 0
b1010000 /
b1010000 .
bx -
bx ,
b10 +
b0 *
b10100 )
b1010000 (
b10 '
x&
0%
b10100 $
b1010000 #
b0 "
b1010000 !
$end
#10
0D"
0N"
0X"
0b"
1l"
0v"
1"#
b1010000 ,
b1010000 6
b1010000 #$
0,#
0O"
0z"
0{"
0|"
0Y"
0&#
0'#
0(#
0;"
0f"
0g"
0h"
1<"
1="
1>"
1@"
1c"
0E"
0p"
0q"
0r"
0F"
0G"
0H"
0J"
0m"
1P"
1Q"
1R"
1T"
1w"
0Z"
0["
0\"
0^"
0d"
0n"
0x"
0##
0$#
0f
0p
0R
1z
0\
0&"
10"
b1010000 9
0:"
0I
0a
0b
0*"
0S
0k
0l
04"
0J
0K
0L
0]
0u
0v
0T
0U
0V
0g
0!"
0""
1^
1_
1`
1q
1+"
1,"
0h
0i
0j
0{
05"
06"
1N
1r
1s
1t
1'"
0X
0|
0}
0~
0("
01"
02"
06#
0@#
0J#
0T#
1^#
0h#
1r#
b1010000 8
0|#
b0 :
b0 H
b0 C"
b0 M"
b0 W"
b0 a"
b0 k"
b0 u"
b0 !#
b0 +#
b0 ;
b0 D
b0 Q
b0 [
b0 e
b0 o
b0 y
b0 %"
b0 /"
b0 9"
b0 <
b0 @
b0 5#
b0 ?#
b0 I#
b0 S#
b0 ]#
b0 g#
b0 q#
b0 {#
0G
1C
0?
b10 -
b10 7
b10 !$
b1010000 !
b1010000 .
b1010000 $$
1&
1%
#20
1X"
b10100 ,
b10100 6
b10100 #$
0"#
1O"
1z"
1{"
1|"
0P"
0Q"
0R"
0T"
0w"
1f
b10100 9
00"
b1100100 !
b1100100 .
b1100100 $$
b1100100 /
b1100100 3
b1100100 "$
b1 ;
b1 D
b1 Q
b1 [
b1 e
b1 o
b1 y
b1 %"
b1 /"
b1 9"
0%
b1 "
b1 *
b1 2
b1 5
b1 >
b1 B
b1 F
#30
b10100 !
b10100 .
b10100 $$
1%
#40
b111100 !
b111100 .
b111100 $$
b111100 /
b111100 3
b111100 "$
b10 ;
b10 D
b10 Q
b10 [
b10 e
b10 o
b10 y
b10 %"
b10 /"
b10 9"
0%
b10 "
b10 *
b10 2
b10 5
b10 >
b10 B
b10 F
#50
0O"
0z"
0{"
0|"
1P"
1Q"
1R"
1T"
1w"
1D"
1X"
b101 ,
b101 6
b101 #$
0l"
0f
b1010000 9
10"
b10 :
b10 H
b10 C"
b10 M"
b10 W"
b10 a"
b10 k"
b10 u"
b10 !#
b10 +#
b0 ;
b0 D
b0 Q
b0 [
b0 e
b0 o
b0 y
b0 %"
b0 /"
b0 9"
1G
0C
b100 -
b100 7
b100 !$
b101 !
b101 .
b101 $$
0&
1%
#60
b10000 !
b10000 .
b10000 $$
b10000 /
b10000 3
b10000 "$
b11 :
b11 H
b11 C"
b11 M"
b11 W"
b11 a"
b11 k"
b11 u"
b11 !#
b11 +#
0%
b11 "
b11 *
b11 2
b11 5
b11 >
b11 B
b11 F
#70
b101 !
b101 .
b101 $$
1%
#80
0D"
b0 ,
b0 6
b0 #$
0X"
b1010100 !
b1010100 .
b1010100 $$
b1010100 /
b1010100 3
b1010100 "$
b100 :
b100 H
b100 C"
b100 M"
b100 W"
b100 a"
b100 k"
b100 u"
b100 !#
b100 +#
0%
b100 "
b100 *
b100 2
b100 5
b100 >
b100 B
b100 F
#90
0<"
0="
0>"
0@"
0c"
0l"
b1000000 ,
b1000000 6
b1000000 #$
1"#
b1000000 9
0z
b0 :
b0 H
b0 C"
b0 M"
b0 W"
b0 a"
b0 k"
b0 u"
b0 !#
b0 +#
b100 ;
b100 D
b100 Q
b100 [
b100 e
b100 o
b100 y
b100 %"
b100 /"
b100 9"
0G
1C
b10 -
b10 7
b10 !$
b1000000 !
b1000000 .
b1000000 $$
1&
1%
#100
b1000001 ,
b1000001 6
b1000001 #$
1D"
1;"
1f"
1g"
1h"
b1000001 9
1R
b10101111 !
b10101111 .
b10101111 $$
b10101111 /
b10101111 3
b10101111 "$
b101 ;
b101 D
b101 Q
b101 [
b101 e
b101 o
b101 y
b101 %"
b101 /"
b101 9"
0%
b101 "
b101 *
b101 2
b101 5
b101 >
b101 B
b101 F
#110
0;"
0f"
0g"
0h"
1<"
1="
1>"
1@"
1c"
1D"
1X"
0l"
b101 ,
b101 6
b101 #$
0"#
0R
b1010000 9
1z
b101 :
b101 H
b101 C"
b101 M"
b101 W"
b101 a"
b101 k"
b101 u"
b101 !#
b101 +#
b0 ;
b0 D
b0 Q
b0 [
b0 e
b0 o
b0 y
b0 %"
b0 /"
b0 9"
1G
0C
b100 -
b100 7
b100 !$
b101 !
b101 .
b101 $$
0&
1%
#120
0X"
1N"
b11 ,
b11 6
b11 #$
0b"
1E"
1p"
1q"
1r"
0Y"
0&#
0'#
0(#
0O"
0z"
0{"
0|"
1;"
1f"
1g"
1h"
0<"
0="
0>"
0@"
0c"
0P"
0Q"
0R"
0T"
0w"
b10 ;
b10 D
b10 Q
b10 [
b10 e
b10 o
b10 y
b10 %"
b10 /"
b10 9"
1\
0p
0f
1R
0z
b11 9
00"
0G
1C
1I
1a
1b
1*"
1S
1k
1l
14"
1J
1K
1L
1]
1u
1v
1T
1U
1V
1g
1!"
1""
0^
0_
0`
0q
0+"
0,"
0N
0r
0s
0t
0'"
b10 -
b10 7
b10 !$
16#
1@#
1J#
1T#
0^#
b1111 8
0r#
b11110101 !
b11110101 .
b11110101 $$
b0 :
b0 H
b0 C"
b0 M"
b0 W"
b0 a"
b0 k"
b0 u"
b0 !#
b0 +#
b10 }#
b11110101 /
b11110101 3
b11110101 "$
1-#
1.#
1/#
10#
17#
18#
19#
1:#
1;#
1<#
1A#
1B#
1C#
1D#
1E#
1F#
1K#
0L#
0M#
0N#
1O#
1P#
0U#
1Y#
1Z#
0`#
0a#
0b#
0c#
0d#
0i#
1v#
0w#
0x#
0%
b10 "
b10 *
b10 2
b10 5
b10 >
b10 B
b10 F
b11010 $
b11010 )
b11010 1
b1111 #
b1111 (
b1111 0
b1111 4
#130
0D"
1X"
1b"
1l"
1v"
1"#
b11111110 ,
b11111110 6
b11111110 #$
1,#
1O"
1z"
1{"
1|"
0E"
0p"
0q"
0r"
1F"
1G"
1H"
1J"
1m"
1P"
1Q"
1R"
1T"
1w"
1Z"
1["
1\"
1^"
1d"
1n"
1x"
1##
1$#
b1 :
b1 H
b1 C"
b1 M"
b1 W"
b1 a"
b1 k"
b1 u"
b1 !#
b1 +#
1f
0\
1&"
10"
b11100101 9
1:"
1G
0I
0a
0b
0*"
0T
0U
0V
0g
0!"
0""
1^
1_
1`
1q
1+"
1,"
1X
1|
1}
1~
1("
11"
12"
b110 -
b110 7
b110 !$
b101100 !
b101100 .
b101100 $$
06#
0T#
1^#
b10010110 8
1|#
b1 ;
b1 D
b1 Q
b1 [
b1 e
b1 o
b1 y
b1 %"
b1 /"
b1 9"
b110 }#
b101100 /
b101100 3
b101100 "$
0-#
12#
0;#
0<#
0B#
0C#
0D#
0K#
1L#
1M#
1N#
1U#
0Y#
0Z#
1c#
1d#
1j#
1k#
1l#
1s#
1t#
0v#
b1 "
b1 *
b1 2
b1 5
b1 >
b1 B
b1 F
b10010110 $
b10010110 )
b10010110 1
b10010110 #
b10010110 (
b10010110 0
b10010110 4
